errno_converter.py
http_converter.py
signal_converter.py
errno_converter-0.2.1.dist-info/licenses/LICENSE
lib/__init__.py
lib/converter.py
lib/parser.py
errno_converter-0.2.1.dist-info/METADATA
errno_converter-0.2.1.dist-info/WHEEL
errno_converter-0.2.1.dist-info/entry_points.txt
errno_converter-0.2.1.dist-info/top_level.txt
errno_converter-0.2.1.dist-info/RECORD
