Metadata-Version: 2.4
Name: errno_converter
Version: 0.2.1
Summary: As simple command line tool to convert error numbers (of C errno.h), http status codes and signal numbers to human readable strings or back zu numbers.
Author-email: Heinrich Kießling <heinrich@kiess.link>
License: Creative Commons Legal Code
Project-URL: Homepage, https://github.com/pokulo/errno_converter
Project-URL: Bug Tracker, https://github.com/pokulo/errno_converter/issues
Classifier: Programming Language :: Python :: 3.9
Classifier: License :: CC0 1.0 Universal (CC0 1.0) Public Domain Dedication
Classifier: Operating System :: OS Independent
Requires-Python: >=3.9
License-File: LICENSE
Dynamic: license-file
